numpytypechecker/README.MD
numpytypechecker/__init__.py
numpytypechecker/requirements.txt
numpytypechecker/thirdparty.json
numpytypechecker-0.11.dist-info/LICENSE.rst
numpytypechecker-0.11.dist-info/METADATA
numpytypechecker-0.11.dist-info/WHEEL
numpytypechecker-0.11.dist-info/top_level.txt
numpytypechecker-0.11.dist-info/RECORD
