Metadata-Version: 2.1
Name: numpytypechecker
Version: 0.11
Summary: Check and convert the data type of a NumPy array based on a predefined set of data types.
Home-page: https://github.com/hansalemaos/numpytypechecker
Author: Johannes Fischer
Author-email: aulasparticularesdealemaosp@gmail.com
License: MIT
Keywords: numpytypechecker,np
Classifier: Development Status :: 4 - Beta
Classifier: Programming Language :: Python :: 3 :: Only
Classifier: Programming Language :: Python :: 3.10
Classifier: Topic :: Software Development :: Libraries :: Python Modules
Classifier: Topic :: Utilities
License-File: LICENSE.rst
Requires-Dist: numpy
